opedia/Lagrangian.py
opedia/ML.py
opedia/__init__.py
opedia/db.py
opedia/eddpy.py
opedia/eddy.py
opedia/eddy_iterative.py
opedia/ftle.py
opedia/ftle_iterative.py
opedia/genericDist.py
opedia/plotCruise.py
opedia/plotDepthProfile.py
opedia/plotDist.py
opedia/plotGM.py
opedia/plotMonthly.py
opedia/plotMonthlySTA.py
opedia/plotRegional.py
opedia/plotSection.py
opedia/plotTS.py
opedia/plotXY.py
opedia/timeSeries.py
opedia/vault.py
opedia-0.1.13.dist-info/LICENSE.txt
opedia-0.1.13.dist-info/METADATA
opedia-0.1.13.dist-info/RECORD
opedia-0.1.13.dist-info/WHEEL
opedia-0.1.13.dist-info/top_level.txt
