Metadata-Version: 2.1
Name: opedia
Version: 0.1.13
Summary: Opedia is an open source database service to integrate, visualize, and analyze ocean datasets such as satellite data, in-situ observations, and model outputs.
Home-page: https://github.com/mdashkezari/opedia/tree/master/pypi
Author: Mohammad D. Ashkezari
Author-email: demo.80@gmail.com
License: UNKNOWN
Keywords: ocean oceanography database dataset satellite model in-situ remote sensing machine learning data visualization
Platform: UNKNOWN
Classifier: Development Status :: 3 - Alpha
Classifier: Intended Audience :: Science/Research
Classifier: License :: OSI Approved :: MIT License
Classifier: Programming Language :: Python :: 2.7
Requires-Dist: matplotlib
Requires-Dist: numpy
Requires-Dist: pandas
Requires-Dist: scipy
Requires-Dist: bokeh
Requires-Dist: pyodbc
Requires-Dist: dropbox
